odoo/addons/sm_pocketbook/__init__.py
odoo/addons/sm_pocketbook/__manifest__.py
odoo/addons/sm_pocketbook/models/__init__.py
odoo/addons/sm_pocketbook/models/models_pocketbook_record.py
odoo/addons/sm_pocketbook/models/models_pocketbook_record_history.py
odoo/addons/sm_pocketbook/models/models_sm_member.py
odoo/addons/sm_pocketbook/security/ir.model.access.csv
odoo/addons/sm_pocketbook/views/views_members.xml
odoo/addons/sm_pocketbook/views/views_pocketbook_record.xml
odoo/addons/sm_pocketbook/views/views_pocketbook_record_history.xml
odoo12_addon_sm_pocketbook-12.0.0.0.9.dist-info/METADATA
odoo12_addon_sm_pocketbook-12.0.0.0.9.dist-info/WHEEL
odoo12_addon_sm_pocketbook-12.0.0.0.9.dist-info/top_level.txt
odoo12_addon_sm_pocketbook-12.0.0.0.9.dist-info/RECORD
