Metadata-Version: 2.1
Name: odoo12-addon-sm-pocketbook
Version: 12.0.0.0.9
Summary: This module is used to have full control over pocketbook actions into the sytem.
Home-page: http://www.sommobilitat.coop
Author: Som Mobilitat
License: UNKNOWN
Platform: UNKNOWN
Classifier: Programming Language :: Python
Classifier: Framework :: Odoo
Classifier: Framework :: Odoo :: 12.0
Requires-Python: >=3.5
Requires-Dist: odoo12-addon-sm-partago-tariffs
Requires-Dist: odoo12-addon-vertical-carsharing
Requires-Dist: odoo (<12.1dev,>=12.0a)
